swarm_squad_ep2/__init__.py
swarm_squad_ep2/main.py
swarm_squad_ep2/api/__init__.py
swarm_squad_ep2/api/database.py
swarm_squad_ep2/api/main.py
swarm_squad_ep2/api/models.py
swarm_squad_ep2/api/utils.py
swarm_squad_ep2/api/vehicle_sim.db-shm
swarm_squad_ep2/api/vehicle_sim.db-wal
swarm_squad_ep2/api/routers/__init__.py
swarm_squad_ep2/api/routers/batch.py
swarm_squad_ep2/api/routers/llms.py
swarm_squad_ep2/api/routers/realtime.py
swarm_squad_ep2/api/routers/veh2llm.py
swarm_squad_ep2/api/routers/vehicles.py
swarm_squad_ep2/api/static/favicon.ico
swarm_squad_ep2/api/templates/index.html
swarm_squad_ep2/cli/__init__.py
swarm_squad_ep2/cli/build.py
swarm_squad_ep2/cli/fastapi.py
swarm_squad_ep2/cli/install.py
swarm_squad_ep2/cli/launch.py
swarm_squad_ep2/cli/sim.py
swarm_squad_ep2/cli/utils.py
swarm_squad_ep2/cli/webui.py
swarm_squad_ep2/scripts/__init__.py
swarm_squad_ep2/scripts/clear_sqlite.py
swarm_squad_ep2/scripts/run_simulation.py
swarm_squad_ep2/scripts/simulator.py
swarm_squad_ep2/scripts/test_client.py
swarm_squad_ep2/scripts/visualize_simulation.py
swarm_squad_ep2/scripts/utils/client.py
swarm_squad_ep2/scripts/utils/message_templates.py
swarm_squad_ep2/web/.eslintrc.json
swarm_squad_ep2/web/.prettierignore
swarm_squad_ep2/web/components.json
swarm_squad_ep2/web/next.config.mjs
swarm_squad_ep2/web/package.json
swarm_squad_ep2/web/pnpm-lock.yaml
swarm_squad_ep2/web/postcss.config.mjs
swarm_squad_ep2/web/tailwind.config.ts
swarm_squad_ep2/web/tsconfig.json
swarm_squad_ep2/web/app/globals.css
swarm_squad_ep2/web/app/layout.tsx
swarm_squad_ep2/web/app/page.tsx
swarm_squad_ep2/web/components/category-header.tsx
swarm_squad_ep2/web/components/chat.tsx
swarm_squad_ep2/web/components/message-input.tsx
swarm_squad_ep2/web/components/sidebar.tsx
swarm_squad_ep2/web/components/theme-provider.tsx
swarm_squad_ep2/web/components/theme-toggle.tsx
swarm_squad_ep2/web/components/ui/accordion.tsx
swarm_squad_ep2/web/components/ui/alert-dialog.tsx
swarm_squad_ep2-0.1.6.dist-info/METADATA
swarm_squad_ep2-0.1.6.dist-info/WHEEL
swarm_squad_ep2-0.1.6.dist-info/entry_points.txt
swarm_squad_ep2-0.1.6.dist-info/licenses/LICENSE
swarm_squad_ep2-0.1.6.dist-info/RECORD
