Metadata-Version: 2.4
Name: swarm-squad-ep2
Version: 0.1.6
Summary: Swarm Squad Ep2: The Digital Dialogue
Project-URL: Homepage, https://swarm-squad.com
Project-URL: Documentation, https://docs.swarm-squad.com
Project-URL: Repository, https://github.com/Swarm-Squad/Swarm-Squad-Ep2
Author-email: Sang Buster <hello@singsongaftermath.com>
License: MIT License
License-File: LICENSE
Requires-Python: >=3.10
Requires-Dist: aiofiles>=24.1.0
Requires-Dist: aiohttp>=3.12.6
Requires-Dist: fastapi>=0.115.12
Requires-Dist: jinja2>=3.1.6
Requires-Dist: matplotlib>=3.10.3
Requires-Dist: motor>=3.7.1
Requires-Dist: numpy>=2.2.6
Requires-Dist: pydantic>=2.11.5
Requires-Dist: pyqt5>=5.15.11
Requires-Dist: sqlmodel>=0.0.24
Requires-Dist: uvicorn>=0.34.2
Requires-Dist: websockets>=15.0.1
